WebDesignTaal/__init__.py
WebDesignTaal/file_handler.py
WebDesignTaal/nodes.py
WebDesignTaal/updater.py
WebDesignTaal/version.txt
WebDesignTaal/wdt_parser.py
webdesigntaal-1.1.5.dist-info/licenses/LICENSE
webdesigntaal-1.1.5.dist-info/METADATA
webdesigntaal-1.1.5.dist-info/WHEEL
webdesigntaal-1.1.5.dist-info/entry_points.txt
webdesigntaal-1.1.5.dist-info/top_level.txt
webdesigntaal-1.1.5.dist-info/RECORD
