Metadata-Version: 2.4
Name: WebDesignTaal
Version: 1.1.5
Summary: Een programmeertaal die compileert naar HTML met een Nederlandse syntax.
Home-page: https://github.com/TJouleL/WebDesignTaal
Author: TJouleL
Keywords: html compiler webdesign educatie
Classifier: Development Status :: 4 - Beta
Classifier: Intended Audience :: Developers
Classifier: Intended Audience :: Education
Classifier: Topic :: Software Development :: Compilers
Classifier: Topic :: Text Processing :: Markup :: HTML
Classifier: License :: OSI Approved :: GNU General Public License v3 (GPLv3)
Classifier: Programming Language :: Python :: 3
Classifier: Programming Language :: Python :: 3.8
Classifier: Programming Language :: Python :: 3.9
Classifier: Programming Language :: Python :: 3.10
Classifier: Programming Language :: Python :: 3.11
Classifier: Operating System :: OS Independent
Requires-Python: >=3.6
License-File: LICENSE
Dynamic: author
Dynamic: classifier
Dynamic: description
Dynamic: description-content-type
Dynamic: home-page
Dynamic: keywords
Dynamic: license-file
Dynamic: requires-python
Dynamic: summary
